sbctl/__init__.py
sbctl-0.0.0.dist-info/METADATA
sbctl-0.0.0.dist-info/WHEEL
sbctl-0.0.0.dist-info/top_level.txt
sbctl-0.0.0.dist-info/RECORD
