Metadata-Version: 2.4
Name: sbctl
Version: 0.0.0
Summary: Coming soon
Author-email: simplyblock <info@simplyblock.io>
